ansible_navigator/__init__.py
ansible_navigator/__main__.py
ansible_navigator/_version.py
ansible_navigator/_version.pyi
ansible_navigator/_version_doc_cache.py
ansible_navigator/action_base.py
ansible_navigator/action_defs.py
ansible_navigator/action_runner.py
ansible_navigator/app_public.py
ansible_navigator/cli.py
ansible_navigator/constants.py
ansible_navigator/content_defs.py
ansible_navigator/diagnostics.py
ansible_navigator/initialization.py
ansible_navigator/logger.py
ansible_navigator/py.typed
ansible_navigator/steps.py
ansible_navigator/version.py
ansible_navigator/actions/__init__.py
ansible_navigator/actions/_actions.py
ansible_navigator/actions/back.py
ansible_navigator/actions/builder.py
ansible_navigator/actions/collections.py
ansible_navigator/actions/config.py
ansible_navigator/actions/doc.py
ansible_navigator/actions/exec.py
ansible_navigator/actions/filter.py
ansible_navigator/actions/help_doc.py
ansible_navigator/actions/images.py
ansible_navigator/actions/inventory.py
ansible_navigator/actions/lint.py
ansible_navigator/actions/log.py
ansible_navigator/actions/open_file.py
ansible_navigator/actions/quit.py
ansible_navigator/actions/refresh.py
ansible_navigator/actions/replay.py
ansible_navigator/actions/rerun.py
ansible_navigator/actions/run.py
ansible_navigator/actions/sample_form.py
ansible_navigator/actions/sample_notification.py
ansible_navigator/actions/sample_working.py
ansible_navigator/actions/save.py
ansible_navigator/actions/select.py
ansible_navigator/actions/serialize_json.py
ansible_navigator/actions/serialize_yaml.py
ansible_navigator/actions/settings.py
ansible_navigator/actions/stdout.py
ansible_navigator/actions/template.py
ansible_navigator/actions/welcome.py
ansible_navigator/actions/write_file.py
ansible_navigator/command_runner/__init__.py
ansible_navigator/command_runner/command_runner.py
ansible_navigator/configuration_subsystem/__init__.py
ansible_navigator/configuration_subsystem/configurator.py
ansible_navigator-26.1.1.dist-info/licenses/LICENSE
ansible_navigator-26.1.1.dist-info/METADATA
ansible_navigator-26.1.1.dist-info/WHEEL
ansible_navigator-26.1.1.dist-info/entry_points.txt
ansible_navigator-26.1.1.dist-info/top_level.txt
ansible_navigator-26.1.1.dist-info/RECORD
