Metadata-Version: 2.4
Name: ansible-navigator
Version: 26.1.1
Summary: A text-based user interface (TUI) for the Red Hat Ansible Automation Platform
Author-email: "Bradley A. Thornton" <bthornto@redhat.com>
Maintainer-email: Ansible by Red Hat <info@ansible.com>
License: Apache
Project-URL: changelog, https://github.com/ansible/ansible-navigator/releases
Project-URL: documentation, https://ansible-navigator.readthedocs.io/en/latest/
Project-URL: homepage, https://github.com/ansible/ansible-navigator
Project-URL: repository, https://github.com/ansible/ansible-navigator
Keywords: ansible
Classifier: Development Status :: 5 - Production/Stable
Classifier: Intended Audience :: Developers
Classifier: License :: OSI Approved :: Apache Software License
Classifier: Operating System :: OS Independent
Classifier: Topic :: Software Development :: Testing
Classifier: Topic :: Software Development :: Quality Assurance
Classifier: Topic :: Utilities
Classifier: Programming Language :: Python
Classifier: Programming Language :: Python :: 3
Classifier: Programming Language :: Python :: 3 :: Only
Classifier: Programming Language :: Python :: 3.10
Classifier: Programming Language :: Python :: 3.11
Classifier: Programming Language :: Python :: 3.12
Classifier: Programming Language :: Python :: 3.13
Classifier: Programming Language :: Python :: Implementation :: CPython
Classifier: Programming Language :: Python :: Implementation :: PyPy
Requires-Python: >=3.10
License-File: LICENSE
Requires-Dist: ansible-builder>=3.0.0
Requires-Dist: ansible-runner<3,>=2.3.1
Requires-Dist: ansible-lint>=6.19.0
Requires-Dist: jinja2
Requires-Dist: jsonschema
Requires-Dist: onigurumacffi<2,>=1.1.0
Requires-Dist: pyyaml
Requires-Dist: setuptools>=63.1.0; python_version >= "3.11"
Requires-Dist: tzdata
Provides-Extra: docs
Requires-Dist: mkdocs-ansible>=24.3.0; extra == "docs"
Provides-Extra: test
Requires-Dist: ansible-core; extra == "test"
Requires-Dist: coverage-enable-subprocess; extra == "test"
Requires-Dist: coverage[toml]>=7.4.3; extra == "test"
Requires-Dist: darglint; extra == "test"
Requires-Dist: flake8-docstrings; extra == "test"
Requires-Dist: libtmux>=0.36.0; extra == "test"
Requires-Dist: pre-commit; extra == "test"
Requires-Dist: pytest-env; extra == "test"
Requires-Dist: pytest-mock; extra == "test"
Requires-Dist: pytest-plus; extra == "test"
Requires-Dist: pytest-subtests; extra == "test"
Requires-Dist: pytest-xdist; extra == "test"
Dynamic: license-file
